skrelief/__init__.py
skrelief/boostedsurf.py
skrelief/ecrelieff.py
skrelief/irelief.py
skrelief/iterative_relief.py
skrelief/multisurf.py
skrelief/multisurfstar.py
skrelief/relief.py
skrelief/relieff.py
skrelief/reliefmss.py
skrelief/reliefseq.py
skrelief/surf.py
skrelief/surfstar.py
skrelief/swrfstar.py
skrelief/turf.py
skrelief/vlsrelief.py
skrelief-0.1.dist-info/LICENSE
skrelief-0.1.dist-info/METADATA
skrelief-0.1.dist-info/WHEEL
skrelief-0.1.dist-info/top_level.txt
skrelief-0.1.dist-info/RECORD
