Metadata-Version: 2.1
Name: skrelief
Version: 0.1
Summary: scikit-learn compatible interface to a number of Relief-based feature selection algorithms
Home-page: https://github.com/jernejvivod/skrelief
Author: Jernej Vivod
Author-email: vivod.jernej@gmail.com
License: MIT
Keywords: data mining,feature selection,feature evaluation,machine learning,data analysis,artificial intelligence,data science
Platform: UNKNOWN
Classifier: Intended Audience :: Developers
Classifier: Intended Audience :: Information Technology
Classifier: Intended Audience :: Science/Research
Classifier: License :: OSI Approved :: MIT License
Classifier: Programming Language :: Python :: 3
Classifier: Programming Language :: Python :: 3.4
Classifier: Programming Language :: Python :: 3.5
Classifier: Programming Language :: Python :: 3.6
Classifier: Programming Language :: Python :: 3.7
Classifier: Topic :: Utilities
Requires-Dist: numpy
Requires-Dist: scipy
Requires-Dist: sklearn
Requires-Dist: julia
